geosparqllib/__init__.py
geosparqllib/functions.py
geosparqllib-0.1.4.dist-info/LICENSE
geosparqllib-0.1.4.dist-info/WHEEL
geosparqllib-0.1.4.dist-info/METADATA
geosparqllib-0.1.4.dist-info/RECORD
