Metadata-Version: 2.1
Name: geosparqllib
Version: 0.1.4
Summary: A Python functions library for working with GeoSPARQL data
License: BSD 3-clause
Author: Nicholas Car
Author-email: nick@kurrawong.ai
Requires-Python: >=3.11,<4.0
Classifier: License :: Other/Proprietary License
Classifier: Programming Language :: Python :: 3
Classifier: Programming Language :: Python :: 3.11
Requires-Dist: rdflib (>=7.0.0,<8.0.0)
Requires-Dist: shapely (>=2.0.4,<3.0.0)
